autoclustering/__init__.py
autoclustering/_version.py
autoclustering/autoclustering.py
autoclustering/pipelines.py
autoclustering/utils.py
autoclustering/configs/__init__.py
autoclustering/configs/clustering.py
autoclustering/configs/dimensionality.py
autoclustering/configs/preprocessing.py
auto_clustering-0.1.0.dev0.dist-info/LICENSE
auto_clustering-0.1.0.dev0.dist-info/METADATA
auto_clustering-0.1.0.dev0.dist-info/WHEEL
auto_clustering-0.1.0.dev0.dist-info/top_level.txt
auto_clustering-0.1.0.dev0.dist-info/RECORD
