Metadata-Version: 2.1
Name: auto-clustering
Version: 0.1.0.dev0
Summary: Automatic Clustering selection with Ray Tune
Home-page: https://github.com/rodrigo-arenas/auto-clustering
Author: Rodrigo Arenas
Author-email: rodrigo.arenas456@gmail.com
License: MIT
Project-URL: Documentation, https://auto-clustering.readthedocs.io/en/stable/
Project-URL: Source Code, https://github.com/rodrigo-arenas/auto-clustering
Project-URL: Bug Tracker, https://github.com/rodrigo-arenas/auto-clustering/issues
Classifier: License :: OSI Approved :: MIT License
Classifier: Programming Language :: Python :: 3
Classifier: Programming Language :: Python :: 3.9
Classifier: Programming Language :: Python :: 3.10
Requires-Python: >=3.9
License-File: LICENSE
Requires-Dist: scikit-learn (>=1.1.0)
Requires-Dist: numpy (>=1.19.0)
Requires-Dist: ray[tune] (>=2.3.0)
Requires-Dist: optuna (>=3.0.0)
Requires-Dist: dirty-cat (>=0.4.0)
Requires-Dist: hdbscan (>=0.8.27)
